dot_kernel/__init__.py
dot_kernel/__main__.py
dot_kernel/imgsize.py
dot_kernel/kernel.py
dot_kernel-0.1.9.data/scripts/install-dot-kernel
dot_kernel_spec/__init__.py
dot_kernel_spec/kernel.json
dot_kernel-0.1.9.dist-info/METADATA
dot_kernel-0.1.9.dist-info/WHEEL
dot_kernel-0.1.9.dist-info/top_level.txt
dot_kernel-0.1.9.dist-info/RECORD
