Metadata-Version: 2.4
Name: dot_kernel
Version: 0.1.9
Summary: Writing dot language and render in jupyter.
Home-page: https://github.com/laixintao/jupyter-dot-kernel
Author: laixintao
Author-email: laixintao1995@163.com
Requires-Dist: graphviz
Requires-Dist: jupyter
Dynamic: author
Dynamic: author-email
Dynamic: home-page
Dynamic: requires-dist
Dynamic: summary
